rebrowser_playwright/__init__.py
rebrowser_playwright/__main__.py
rebrowser_playwright/_repo_version.py
rebrowser_playwright/py.typed
rebrowser_playwright/_impl/__init__.py
rebrowser_playwright/_impl/_accessibility.py
rebrowser_playwright/_impl/_api_structures.py
rebrowser_playwright/_impl/_artifact.py
rebrowser_playwright/_impl/_assertions.py
rebrowser_playwright/_impl/_async_base.py
rebrowser_playwright/_impl/_browser.py
rebrowser_playwright/_impl/_browser_context.py
rebrowser_playwright/_impl/_browser_type.py
rebrowser_playwright/_impl/_cdp_session.py
rebrowser_playwright/_impl/_clock.py
rebrowser_playwright/_impl/_connection.py
rebrowser_playwright/_impl/_console_message.py
rebrowser_playwright/_impl/_dialog.py
rebrowser_playwright/_impl/_download.py
rebrowser_playwright/_impl/_driver.py
rebrowser_playwright/_impl/_element_handle.py
rebrowser_playwright/_impl/_errors.py
rebrowser_playwright/_impl/_event_context_manager.py
rebrowser_playwright/_impl/_fetch.py
rebrowser_playwright/_impl/_file_chooser.py
rebrowser_playwright/_impl/_frame.py
rebrowser_playwright/_impl/_glob.py
rebrowser_playwright/_impl/_greenlets.py
rebrowser_playwright/_impl/_har_router.py
rebrowser_playwright/_impl/_helper.py
rebrowser_playwright/_impl/_impl_to_api_mapping.py
rebrowser_playwright/_impl/_input.py
rebrowser_playwright/_impl/_js_handle.py
rebrowser_playwright/_impl/_json_pipe.py
rebrowser_playwright/_impl/_local_utils.py
rebrowser_playwright/_impl/_locator.py
rebrowser_playwright/_impl/_map.py
rebrowser_playwright/_impl/_network.py
rebrowser_playwright/_impl/_object_factory.py
rebrowser_playwright/_impl/_page.py
rebrowser_playwright/_impl/_path_utils.py
rebrowser_playwright/_impl/_playwright.py
rebrowser_playwright/_impl/_selectors.py
rebrowser_playwright/_impl/_set_input_files_helpers.py
rebrowser_playwright/_impl/_str_utils.py
rebrowser_playwright/_impl/_stream.py
rebrowser_playwright/_impl/_sync_base.py
rebrowser_playwright/_impl/_tracing.py
rebrowser_playwright-1.52.0.dist-info/LICENSE
rebrowser_playwright-1.52.0.dist-info/METADATA
rebrowser_playwright-1.52.0.dist-info/WHEEL
rebrowser_playwright-1.52.0.dist-info/entry_points.txt
rebrowser_playwright-1.52.0.dist-info/top_level.txt
rebrowser_playwright-1.52.0.dist-info/RECORD
