Metadata-Version: 2.1
Name: rebrowser_playwright
Version: 1.52.0
Summary: A high-level API to automate web browsers
Author: Microsoft Corporation
License: Apache-2.0
Project-URL: homepage, https://github.com/rebrowser/rebrowser-playwright-python
Project-URL: Release notes, https://github.com/rebrowser/rebrowser-playwright-python/releases
Classifier: Topic :: Software Development :: Testing
Classifier: Topic :: Internet :: WWW/HTTP :: Browsers
Classifier: Intended Audience :: Developers
Classifier: Programming Language :: Python :: 3
Classifier: Programming Language :: Python :: 3.9
Classifier: Programming Language :: Python :: 3.10
Classifier: Programming Language :: Python :: 3.11
Classifier: Programming Language :: Python :: 3.12
Classifier: Programming Language :: Python :: 3.13
Classifier: Operating System :: OS Independent
Requires-Python: >=3.9
License-File: LICENSE
Requires-Dist: pyee <14,>=13
Requires-Dist: greenlet <4.0.0,>=3.1.1
